{
    "信息流（官网包）": [{
            "0": "渠道类别",
            "1": "渠道名称",
            "2": "渠道id",
            "3": "渠道包",
            "4": "渠道目标",
            "5": "账户ID",
            "6": "转化ID",
            "7": "备注"
        },
        {
            "0": "信息流（榕易有钱）",
            "1": "抖音剧星（榕易有钱）",
            "2": "wallet_dyjx3",
            "3": "wallet_gw2",
            "4": "toutiao"
        },
        {
            "0": "信息流（榕易有钱）",
            "1": "抖音剧星（榕易有钱）",
            "2": "wallet_dyjx4",
            "3": "wallet_gw2",
            "4": "toutiao"
        },
        {
            "0": "信息流（榕易有钱）",
            "1": "抖音剧星（榕易有钱）",
            "2": "wallet_dyjx5",
            "3": "wallet_gw2",
            "4": "toutiao"
        },
        {
            "0": "信息流（榕易有钱）",
            "1": "抖音剧星（榕易有钱）",
            "2": "wallet_dyjx6",
            "3": "wallet_gw2",
            "4": "toutiao"
        },
        {
            "0": "信息流（榕易有钱）",
            "1": "抖音剧星（榕易有钱）",
            "2": "wallet_dyjx7",
            "3": "wallet_gw2",
            "4": "toutiao"
        },
        {
            "0": "信息流（榕易有钱）",
            "1": "抖音剧星（榕易有钱）",
            "2": "wallet_dyjx8",
            "3": "wallet_gw2",
            "4": "toutiao"
        },
        {
            "0": "信息流（榕易有钱）",
            "1": "抖音剧星（榕易有钱）",
            "2": "wallet_dyjx9",
            "3": "wallet_gw2",
            "4": "toutiao"
        },
        {
            "0": "信息流（榕易有钱）",
            "1": "抖音剧星（榕易有钱）",
            "2": "wallet_dyjx10",
            "3": "wallet_gw2",
            "4": "toutiao"
        },
        {
            "0": "信息流（榕易有钱）",
            "1": "广点通极光（榕易有钱）",
            "2": "wallet_gdtjg1",
            "3": "wallet_gw2",
            "4": "gdt",
            "5": 9950164,
            "6": 1108793536
        },
        {
            "0": "信息流（榕易有钱）",
            "1": "广点通极光（榕易有钱）",
            "2": "wallet_gdtjg2",
            "3": "wallet_gw2",
            "4": "gdt",
            "5": 9950164,
            "6": 1108793536
        },
        {
            "0": "信息流（榕易有钱）",
            "1": "广点通极光（榕易有钱）",
            "2": "wallet_gdtjg3",
            "3": "wallet_gw2",
            "4": "gdt",
            "5": 9950164,
            "6": 1108793536
        },
        {
            "0": "信息流（榕易有钱）",
            "1": "广点通极光（榕易有钱）",
            "2": "wallet_gdtjg4",
            "3": "wallet_gw2",
            "4": "gdt",
            "5": 9950164,
            "6": 1108793536
        },
        {
            "0": "信息流（榕易有钱）",
            "1": "广点通极光（榕易有钱）",
            "2": "wallet_gdtjg5",
            "3": "wallet_gw2",
            "4": "gdt",
            "5": 9950164,
            "6": 1108793536
        },
        {
            "0": "信息流（榕易有钱）",
            "1": "广点通极光（榕易有钱）",
            "2": "wallet_gdtjg6",
            "3": "wallet_gw2",
            "4": "gdt",
            "5": 9950164,
            "6": 1108793536
        },
        {}
    ],
    "异业渠道（官网包）": [{
            "0": "渠道类别",
            "1": "渠道名称",
            "2": "渠道id",
            "3": "渠道包",
            "4": "渠道目标",
            "5": "账户ID",
            "6": "转化ID",
            "7": "备注"
        },
        {
            "0": "异业合作（榕易有钱）",
            "1": "骏伯网络（榕易有钱）",
            "2": "wallet_jbwlapp1",
            "3": "wallet_jbwlapp1",
            "7": "韩昱占用"
        },
        {
            "0": "异业合作（榕易有钱）",
            "1": "骏伯网络（榕易有钱）",
            "2": "wallet_jbwlapp2",
            "3": "wallet_jbwlapp2",
            "7": "韩昱占用"
        },
        {
            "0": "异业合作（榕易有钱）",
            "1": "鑫安满（榕易有钱）",
            "2": "wallet_xam1",
            "3": "wallet_gw2",
            "4": "kuaishou",
            "7": "韩昱占用"
        },
        {
            "0": "异业合作（榕易有钱）",
            "1": "鑫安满（榕易有钱）",
            "2": "wallet_xam2",
            "3": "wallet_gw2",
            "4": "kuaishou",
            "7": "韩昱占用"
        },
        {
            "0": "异业合作（榕易有钱）",
            "1": "鑫安满（榕易有钱）",
            "2": "wallet_xam9",
            "3": "wallet_gw2",
            "4": "kuaishou",
            "7": "韩昱占用"
        },
        {
            "0": "异业合作（榕易有钱）",
            "1": "鑫安满（榕易有钱）",
            "2": "wallet_xam10",
            "3": "wallet_gw2",
            "4": "kuaishou",
            "7": "韩昱占用"
        },
        {
            "0": "异业合作（榕易有钱）",
            "1": "鑫安满（榕易有钱）",
            "2": "wallet_xam11",
            "3": "wallet_gw2",
            "4": "kuaishou",
            "7": "韩昱占用"
        },
        {
            "0": "异业合作（榕易有钱）",
            "1": "鑫安满（榕易有钱）",
            "2": "wallet_xam12",
            "3": "wallet_gw2",
            "4": "kuaishou",
            "7": "韩昱占用"
        },
        {
            "0": "异业合作（榕易有钱）",
            "1": "51信用卡（榕易有钱）",
            "2": "wallet_51xyk2",
            "3": "wallet_gw2",
            "7": "韩昱占用"
        },
        {
            "0": "异业合作（榕易有钱）",
            "1": "51信用卡（榕易有钱）",
            "2": "wallet_51xyk3",
            "3": "wallet_gw2",
            "7": "韩昱占用"
        },
        {
            "0": "异业合作（榕易有钱）",
            "1": "51信用卡（榕易有钱）",
            "2": "wallet_51xyk4",
            "3": "wallet_gw2",
            "7": "韩昱占用"
        },
        {
            "0": "异业合作（榕易有钱）",
            "1": "51信用卡（榕易有钱）",
            "2": "wallet_51xyk5",
            "3": "wallet_gw2",
            "7": "韩昱占用"
        },
        {
            "0": "异业合作（榕易有钱）",
            "1": "OFO（榕易有钱）",
            "2": "wallet_ofo1",
            "3": "wallet_gw2",
            "7": "邵火琴占用"
        },
        {
            "0": "垂直渠道（榕易有钱）",
            "1": "浦发（榕易有钱）",
            "2": "wallet_pf1",
            "3": "wallet_gw2",
            "7": "胡佩延申请"
        },
        {
            "0": "垂直渠道（榕易有钱）",
            "1": "借了吗（榕易有钱）",
            "2": "wallet_jlm1",
            "3": "wallet_gw2",
            "7": "陈思占用"
        },
        {
            "0": "垂直渠道（榕易有钱）",
            "1": "借了吗（榕易有钱）",
            "2": "wallet_jlm2",
            "3": "wallet_gw2",
            "7": "陈思占用"
        },
        {
            "0": "垂直渠道（榕易有钱）",
            "1": "借了吗（榕易有钱）",
            "2": "wallet_jlm3",
            "3": "wallet_gw2",
            "7": "陈思占用"
        },
        {
            "0": "垂直渠道（榕易有钱）",
            "1": "熊猫贷款（榕易有钱）",
            "2": "wallet_xmdk1",
            "3": "wallet_gw2",
            "7": "陈思占用"
        }
    ],
    "自有渠道": [{
            "0": "渠道类别",
            "1": "渠道名称",
            "2": "渠道id",
            "3": "渠道包",
            "7": "备注"
        },
        {
            "0": "自有渠道（榕易有钱）",
            "1": "榕易有钱官网",
            "2": "wallet_gw1",
            "3": "wallet_gw1"
        },
        {
            "0": "自有渠道（榕易有钱）",
            "1": "榕易有钱官网",
            "2": "wallet_gw2",
            "3": "wallet_gw2"
        },
        {
            "0": "自有渠道（榕易有钱）",
            "1": "落地页登录（榕易有钱）",
            "2": "wallet_ldy1",
            "3": "wallet_ldy1"
        },
        {}
    ]
}